arabic_support/__init__.py
arabic_support/arabic_supprt.py
streamlit_arabic_support_wrapper-1.1.dist-info/LICENSE
streamlit_arabic_support_wrapper-1.1.dist-info/METADATA
streamlit_arabic_support_wrapper-1.1.dist-info/WHEEL
streamlit_arabic_support_wrapper-1.1.dist-info/top_level.txt
streamlit_arabic_support_wrapper-1.1.dist-info/RECORD
