Metadata-Version: 2.1
Name: streamlit_arabic_support_wrapper
Version: 1.1
Summary: A simple component to perfectly align Arabic text in Streamlit Apps.
Home-page: https://github.com/baselhusam/streamlit_arabic_support_wrapper
Author: Basel Husam
Author-email: baselmathar@gmail.com
License: Apache 2
Classifier: Programming Language :: Python :: 3
Classifier: License :: OSI Approved :: Apache Software License
Classifier: Operating System :: OS Independent
Requires-Python: >=3.5
License-File: LICENSE
Requires-Dist: streamlit
